{"BURMY_PLANT": {"ja": "\u304f\u3055\u304d\u306e\u30df\u30ce", "zh-tw": "\u8349\u6728\u84d1\u8863", "fr": "Cape Plante", "de": "Pflanzenumhang", "ko": "\ucd08\ubaa9\ub3c4\ub871", "es": "Tronco Planta", "en": "Plant Cloak", "pt-br": "Manto Vegetal", "it": "Manto Pianta"}, "BURMY_SANDY": {"ja": "\u3059\u306a\u3061\u306e\u30df\u30ce", "zh-tw": "\u7802\u571f\u84d1\u8863", "fr": "Cape Sable", "de": "Sandumhang", "ko": "\ubaa8\ub798\ub545\ub3c4\ub871", "es": "Tronco Arena", "en": "Sandy Cloak", "pt-br": "Manto Arenoso", "it": "Manto Sabbia"}, "BURMY_TRASH": {"ja": "\u30b4\u30df\u306e\u30df\u30ce", "zh-tw": "\u5783\u573e\u84d1\u8863", "fr": "Cape D\u00e9chet", "de": "Lumpenumhang", "ko": "\uc288\ub808\ub3c4\ub871", "es": "Tronco Basura", "en": "Trash Cloak", "pt-br": "Manto de Lixo", "it": "Manto Scarti"}, "CASTFORM_RAINY": {"ja": "\u3042\u307e\u307f\u305a\u306e\u3059\u304c\u305f", "zh-tw": "\u96e8\u6c34\u7684\u6a23\u5b50", "fr": "Eau de Pluie", "de": "Regenform", "ko": "\ube57\ubc29\uc6b8\uc758 \ubaa8\uc2b5", "es": "Lluvia", "en": "Rainy", "pt-br": "Chuvosa", "it": "Pioggia"}, "CASTFORM_SNOWY": {"ja": "\u3086\u304d\u3050\u3082\u306e\u3059\u304c\u305f", "zh-tw": "\u96ea\u96f2\u7684\u6a23\u5b50", "fr": "Blizzard", "de": "Schneeform", "ko": "\uc124\uc6b4\uc758 \ubaa8\uc2b5", "es": "Nieve", "en": "Snowy", "pt-br": "Nevada", "it": "Nuvola di Neve"}, "CASTFORM_SUNNY": {"ja": "\u305f\u3044\u3088\u3046\u306e\u3059\u304c\u305f", "zh-tw": "\u592a\u967d\u7684\u6a23\u5b50", "fr": "Solaire", "de": "Sonnenform", "ko": "\ud0dc\uc591\uc758 \ubaa8\uc2b5", "es": "Sol", "en": "Sunny", "pt-br": "Ensolarada", "it": "Sole"}, "CHERRIM_SUNNY": {"ja": "\u30dd\u30b8\u30d5\u30a9\u30eb\u30e0", "zh-tw": "\u6674\u5929\u5f62\u614b", "fr": "Temps Ensoleill\u00e9", "de": "Sonnenform", "ko": "\ud3ec\uc9c0\ud3fc", "es": "Forma Soleado", "en": "Sunshine Form", "pt-br": "Forma Solar", "it": "Forma Splendore"}, "WORMADAM_PLANT": {"ja": "\u304f\u3055\u304d\u306e\u30df\u30ce", "zh-tw": "\u8349\u6728\u84d1\u8863", "fr": "Cape Plante", "de": "Pflanzenumhang", "ko": "\ucd08\ubaa9\ub3c4\ub871", "es": "Tronco Planta", "en": "Plant Cloak", "pt-br": "Manto Vegetal", "it": "Manto Pianta"}, "WORMADAM_SANDY": {"ja": "\u3059\u306a\u3061\u306e\u30df\u30ce", "zh-tw": "\u7802\u571f\u84d1\u8863", "fr": "Cape Sable", "de": "Sandumhang", "ko": "\ubaa8\ub798\ub545\ub3c4\ub871", "es": "Tronco Arena", "en": "Sandy Cloak", "pt-br": "Manto Arenoso", "it": "Manto Sabbia"}, "WORMADAM_TRASH": {"ja": "\u30b4\u30df\u306e\u30df\u30ce", "zh-tw": "\u5783\u573e\u84d1\u8863", "fr": "Cape D\u00e9chet", "de": "Lumpenumhang", "ko": "\uc288\ub808\ub3c4\ub871", "es": "Tronco Basura", "en": "Trash Cloak", "pt-br": "Manto de Lixo", "it": "Manto Scarti"}, "form_alola": {"ja": "\u30a2\u30ed\u30fc\u30e9\u306e\u3059\u304c\u305f", "zh-tw": "\u963f\u7f85\u62c9\u7684\u6a23\u5b50", "fr": "Forme d\u2019Alola", "de": "Alola-Form", "ko": "\uc54c\ub85c\ub77c\uc758 \ubaa8\uc2b5", "es": "Forma de Alola", "en": "Alolan Form", "pt-br": "Forma de Alola", "it": "Forma di Alola"}}